spriteforhtml/__init__.py
spriteforhtml/__main__.py
spriteforhtml/_sort.py
spriteforhtml/create.py
spriteforhtml/data/english.png
spriteforhtml/data/facebook.png
spriteforhtml/data/france.png
spriteforhtml/data/page.html
spriteforhtml/data/play_20x20.png
spriteforhtml/data/sprite.css
spriteforhtml/data/sprite.json
spriteforhtml/data/sprite.png
spriteforhtml/data/sprite.webp
spriteforhtml/data/youtube.png
spriteforhtml-1.1.2.dist-info/LICENSE
spriteforhtml-1.1.2.dist-info/METADATA
spriteforhtml-1.1.2.dist-info/WHEEL
spriteforhtml-1.1.2.dist-info/top_level.txt
spriteforhtml-1.1.2.dist-info/RECORD
