Metadata-Version: 2.1
Name: spriteforhtml
Version: 1.1.2
Summary: A sprite generator for html, as png and webp, providing associated .css file
Author-email: Pascal Brand <pascal.brand38@gmail.com>
License: UNKNOWN
Project-URL: Homepage, https://github.com/pascal-brand38/py-spriteforhtml
Project-URL: Bug Tracker, https://github.com/pascal-brand38/py-spriteforhtml/issues
Platform: UNKNOWN
Classifier: Programming Language :: Python :: 3
Classifier: License :: OSI Approved :: MIT License
Classifier: Operating System :: OS Independent
Requires-Python: >=3.8
License-File: LICENSE
Requires-Dist: Pillow
